mpl_data_containers/__init__.py
mpl_data_containers/artist.py
mpl_data_containers/axes.py
mpl_data_containers/containers.py
mpl_data_containers/conversion_edge.py
mpl_data_containers/conversion_node.py
mpl_data_containers/description.py
mpl_data_containers/image.py
mpl_data_containers/introspection.py
mpl_data_containers/line.py
mpl_data_containers/patches.py
mpl_data_containers/text.py
mpl_data_containers/wrappers.py
mpl_data_containers/tests/__init__.py
mpl_data_containers/tests/conftest.py
mpl_data_containers/tests/test_check_shape.py
mpl_data_containers/tests/test_containers.py
mpl_data_containers/tests/test_examples.py
mpl_data_containers-0.1.4.dist-info/licenses/AUTHORS.rst
mpl_data_containers-0.1.4.dist-info/licenses/LICENSE
mpl_data_containers-0.1.4.dist-info/METADATA
mpl_data_containers-0.1.4.dist-info/WHEEL
mpl_data_containers-0.1.4.dist-info/top_level.txt
mpl_data_containers-0.1.4.dist-info/RECORD
