Metadata-Version: 2.4
Name: mpl_data_containers
Version: 0.1.4
Summary: Experimental code for the upcoming Matplotlib data refactor.
Home-page: https://github.com/matplotlib/data-prototype
Author: Kyle Sunden
Author-email: pypi@ksunden.space
License: BSD (3-clause)
Classifier: Development Status :: 2 - Pre-Alpha
Classifier: Natural Language :: English
Classifier: Programming Language :: Python :: 3
Requires-Python: >=3.10
License-File: LICENSE
License-File: AUTHORS.rst
Requires-Dist: cachetools
Requires-Dist: matplotlib
Requires-Dist: pandas
Requires-Dist: xarray
Dynamic: author
Dynamic: author-email
Dynamic: classifier
Dynamic: description
Dynamic: home-page
Dynamic: license
Dynamic: license-file
Dynamic: requires-dist
Dynamic: requires-python
Dynamic: summary
